Fiona18ZhongwenWendang/README.md
Fiona18ZhongwenWendang/__init__.py
Fiona18ZhongwenWendang/__main__.py
Fiona18ZhongwenWendang/file.epub
Fiona18ZhongwenWendang/index.html
Fiona18ZhongwenWendang/css/__init__.py
Fiona18ZhongwenWendang/css/annotations.css
Fiona18ZhongwenWendang/css/main.css
Fiona18ZhongwenWendang/css/normalize.css
Fiona18ZhongwenWendang/css/popup.css
Fiona18ZhongwenWendang/font/__init__.py
Fiona18ZhongwenWendang/font/fontello.eot
Fiona18ZhongwenWendang/font/fontello.svg
Fiona18ZhongwenWendang/font/fontello.ttf
Fiona18ZhongwenWendang/font/fontello.woff
Fiona18ZhongwenWendang/img/__init__.py
Fiona18ZhongwenWendang/img/annotator-glyph-sprite.png
Fiona18ZhongwenWendang/img/annotator-icon-sprite.png
Fiona18ZhongwenWendang/img/apple-touch-icon.png
Fiona18ZhongwenWendang/img/cancelfullscreen.png
Fiona18ZhongwenWendang/img/close.png
Fiona18ZhongwenWendang/img/fullscreen.png
Fiona18ZhongwenWendang/img/loader.gif
Fiona18ZhongwenWendang/img/menu-icon.png
Fiona18ZhongwenWendang/img/save.png
Fiona18ZhongwenWendang/img/saved.png
Fiona18ZhongwenWendang/img/settings-s.png
Fiona18ZhongwenWendang/img/settings.png
Fiona18ZhongwenWendang/img/star.png
Fiona18ZhongwenWendang/js/__init__.py
Fiona18ZhongwenWendang/js/epub.js
Fiona18ZhongwenWendang/js/epub.min.js
Fiona18ZhongwenWendang/js/epub.min.map
Fiona18ZhongwenWendang/js/hooks.min.js
Fiona18ZhongwenWendang/js/hooks.min.map
Fiona18ZhongwenWendang/js/reader.js
Fiona18ZhongwenWendang/js/reader.js.map
Fiona18ZhongwenWendang/js/reader.min.js
Fiona18ZhongwenWendang/js/reader.min.map
Fiona18ZhongwenWendang/js/hooks/__init__.py
Fiona18ZhongwenWendang/js/hooks/extensions/__init__.py
Fiona18ZhongwenWendang/js/hooks/extensions/highlight.js
Fiona18ZhongwenWendang/js/libs/__init__.py
Fiona18ZhongwenWendang/js/libs/jquery.min.js
Fiona18ZhongwenWendang/js/libs/localforage.min.js
Fiona18ZhongwenWendang/js/libs/screenfull.js
Fiona18ZhongwenWendang/js/libs/screenfull.min.js
Fiona18ZhongwenWendang/js/libs/zip.min.js
fiona_1_8_zhongwen_wendang-2024.3.4.0.dist-info/METADATA
fiona_1_8_zhongwen_wendang-2024.3.4.0.dist-info/WHEEL
fiona_1_8_zhongwen_wendang-2024.3.4.0.dist-info/entry_points.txt
fiona_1_8_zhongwen_wendang-2024.3.4.0.dist-info/top_level.txt
fiona_1_8_zhongwen_wendang-2024.3.4.0.dist-info/RECORD
